Test_Package12345678MyOwn/Add.py
Test_Package12345678MyOwn/Subtract.py
Test_Package12345678MyOwn/__init__.py
Test_Package12345678MyOwn/Extras/Divide.py
Test_Package12345678MyOwn/Extras/Multiply.py
Test_Package12345678MyOwn/Extras/__init__.py
Test_Package12345678MyOwn-0.0.1.dist-info/METADATA
Test_Package12345678MyOwn-0.0.1.dist-info/WHEEL
Test_Package12345678MyOwn-0.0.1.dist-info/top_level.txt
Test_Package12345678MyOwn-0.0.1.dist-info/RECORD
